riberry_web/__init__.py
riberry_web/__main__.py
riberry_web/app.py
riberry_web/lib/gql/__init__.py
riberry_web/lib/gql/graphene_sqla/__init__.py
riberry_web/lib/gql/graphene_sqla/builder.py
riberry_web/lib/gql/graphene_sqla/fields.py
riberry_web/lib/gql/graphene_sqla/helpers.py
riberry_web/lib/gql/graphene_sqla/loaders/__init__.py
riberry_web/lib/gql/graphene_sqla/loaders/factory.py
riberry_web/lib/gql/graphene_sqla/loaders/pagination.py
riberry_web/lib/gql/graphene_sqla/loaders/relationship.py
riberry_web/lib/gql/graphene_sqla/wrapper_graphene.py
riberry_web/lib/gql/graphene_sqla/wrapper_sqla.py
riberry_web/lib/gql/helpers.py
riberry_web/lib/gql/models.py
riberry_web/lib/gql/mutations.py
riberry_web/lib/gql/objects.py
riberry_web/lib/gql/schema.py
riberry_web/middleware/__init__.py
riberry_web/middleware/auth.py
riberry_web/middleware/database.py
riberry_web/riberry/__init__.py
riberry_web/riberry/policy_context.py
riberry_web/webapp/favicon.ico
riberry_web/webapp/index.html
riberry_web-0.1.2.dist-info/LICENSE
riberry_web-0.1.2.dist-info/WHEEL
riberry_web-0.1.2.dist-info/METADATA
riberry_web-0.1.2.dist-info/RECORD
