Metadata-Version: 2.1
Name: riberry-web
Version: 0.1.2
Summary: 
License: MIT
Author: Shady Rafehi
Author-email: shadyrafehi@gmail.com
Requires-Python: >=3.7,<4.0
Classifier: License :: OSI Approved :: MIT License
Classifier: Programming Language :: Python :: 3
Classifier: Programming Language :: Python :: 3.7
Classifier: Programming Language :: Python :: 3.8
Requires-Dist: fastapi[all] (>=0.45.0,<0.46.0)
Requires-Dist: riberry (>=0.10.21,<0.11.0)
